<annotation>
	<folder>train</folder>
	<filename>23.jpg</filename>
	<path>D:\yolov5\JPEG\train\23.jpg</path>
	<source>
		<database>Unknown</database>
	</source>
	<size>
		<width>800</width>
		<height>533</height>
		<depth>3</depth>
	</size>
	<segmented>0</segmented>
	<object>
		<name>enemy</name>
		<pose>Unspecified</pose>
		<truncated>0</truncated>
		<difficult>0</difficult>
		<bndbox>
			<xmin>426</xmin>
			<ymin>30</ymin>
			<xmax>677</xmax>
			<ymax>524</ymax>
		</bndbox>
	</object>
</annotation>
